py5sim/__init__.py
py5sim/guest.py
py5sim/simfuncs.py
py5sim/simtypes.py
py5sim/sms.py
py5sim/user.py
py5sim-1.0.1.dist-info/WHEEL
py5sim-1.0.1.dist-info/METADATA
py5sim-1.0.1.dist-info/RECORD
